pandas_django_fixtures/__init__.py
pandas_django_fixtures/utils.py
pandas_django_fixtures-0.0.4.dist-info/METADATA
pandas_django_fixtures-0.0.4.dist-info/WHEEL
pandas_django_fixtures-0.0.4.dist-info/licenses/LICENSE
pandas_django_fixtures-0.0.4.dist-info/RECORD
