Metadata-Version: 2.4
Name: pandas-django-fixtures
Version: 0.0.4
Author-email: Kirill Potapov <kdpotapov02@gmail.com>
License-File: LICENSE
Classifier: License :: OSI Approved :: MIT License
Classifier: Operating System :: OS Independent
Classifier: Programming Language :: Python :: 3
Requires-Python: >=3.10.0
Requires-Dist: pandas>=1.0.0
